mirage/__init__.py
mirage/_cert.py
mirage/_ms.py
mirage/_ud.py
mirage/_user_identity.py
mirage/block_forge.py
mirage/http.py
mirage/node.py
mirage/user.py
duniter_mirage-0.1.53.dist-info/LICENSE
duniter_mirage-0.1.53.dist-info/METADATA
duniter_mirage-0.1.53.dist-info/WHEEL
duniter_mirage-0.1.53.dist-info/dependency_links.txt
duniter_mirage-0.1.53.dist-info/top_level.txt
duniter_mirage-0.1.53.dist-info/RECORD
