Metadata-Version: 2.1
Name: duniter-mirage
Version: 0.1.53
Summary: A python mock server of [duniter](https://github.com/duniter/duniter) API
Home-page: https://github.com/Insoleet/mirage
Author: inso
Author-email: inso@tuta.io
License: UNKNOWN
Platform: UNKNOWN
Classifier: Programming Language :: Python
Classifier: Development Status :: 4 - Beta
Classifier: License :: OSI Approved :: GNU General Public License v3 (GPLv3)
Classifier: Natural Language :: French
Classifier: Operating System :: OS Independent
Classifier: Programming Language :: Python :: 3.5
Classifier: Topic :: Communications
